setup.py
pytisean/__init__.py
pytisean/pytisean.py
pytisean.egg-info/PKG-INFO
pytisean.egg-info/SOURCES.txt
pytisean.egg-info/dependency_links.txt
pytisean.egg-info/not-zip-safe
pytisean.egg-info/requires.txt
pytisean.egg-info/top_level.txt