Metadata-Version: 1.0
Name: pytisean
Version: 0.1
Summary: Python wrapper for the TISEAN package
Home-page: https://github.com/bogeholm/pytisean
Author: Troels Bogeholm Mikkelsen
Author-email: bogeholm@nbi.ku.dk
License: MIT
Platform: UNKNOWN
